LICENSE.txt
MANIFEST.in
README.rst
imagerater.py
setup.cfg
setup.py
imagerater.egg-info/PKG-INFO
imagerater.egg-info/SOURCES.txt
imagerater.egg-info/dependency_links.txt
imagerater.egg-info/entry_points.txt
imagerater.egg-info/top_level.txt