Metadata-Version: 1.2
Name: imagerater
Version: 0.1.2
Summary: Simple cmd line tool to display, rate images and then save an imageAndRating matrix.
Home-page: https://github.com/jaza10/imagerater.git
Author: Jan Zawadzki
Author-email: jaza10@me.com
License: MIT
Keywords: image rating classification neural network data gathering imagerater imagerating
Platform: UNKNOWN
Classifier: Development Status :: 3 - Alpha
Classifier: Intended Audience :: Developers
Classifier: Topic :: Software Development :: Build Tools
Classifier: License :: OSI Approved :: MIT License
Classifier: Programming Language :: Python :: 2
Classifier: Programming Language :: Python :: 2.6
Classifier: Programming Language :: Python :: 2.7
Classifier: Programming Language :: Python :: 3
Classifier: Programming Language :: Python :: 3.2
Classifier: Programming Language :: Python :: 3.3
Classifier: Programming Language :: Python :: 3.4
Requires-Python: >=2.6, !=3.0.*, !=3.1.*, !=3.2.*, <4
